lunaconf/__init__.py
lunaconf/cli.py
lunaconf/config_base.py
lunaconf/dump.py
lunaconf/py.typed
lunaconf-0.5.2.dist-info/WHEEL
lunaconf-0.5.2.dist-info/METADATA
lunaconf-0.5.2.dist-info/RECORD
