Metadata-Version: 2.3
Name: lunaconf
Version: 0.5.2
Summary: lunaconf is a Python library to support easy-to-understand configuration for evaluations
Author: Wenrui Huang
Author-email: Wenrui Huang <rijuyuezhuhwr@gmail.com>
License: MIT License
Requires-Dist: pydantic>2
Requires-Dist: toml>=0.10.2
Requires-Python: >=3.11
Project-URL: homepage, https://github.com/rijuyuezhu/lunaconf
